{"__symbolic":"module","version":4,"metadata":{"Alert":{"__symbolic":"interface"},"AlertType":{"None":0,"Success":1,"Error":2,"Warning":3,"Info":4},"CplxAlertService":{"__symbolic":"class","decorators":[{"__symbolic":"call","expression":{"__symbolic":"reference","module":"@angular/core","name":"Injectable","line":19,"character":1},"arguments":[{"providedIn":"root"}]}],"members":{"__ctor__":[{"__symbolic":"constructor","parameters":[{"__symbolic":"reference","module":"@angular/router","name":"Router","line":27,"character":29}]}],"add":[{"__symbolic":"method"}],"getAlertas":[{"__symbolic":"method"}],"clear":[{"__symbolic":"method"}]},"statics":{"ngInjectableDef":{}}},"CplxAlertModule":{"__symbolic":"class","decorators":[{"__symbolic":"call","expression":{"__symbolic":"reference","module":"@angular/core","name":"NgModule","line":7,"character":1},"arguments":[{"imports":[{"__symbolic":"reference","module":"@angular/common","name":"CommonModule","line":8,"character":11},{"__symbolic":"reference","module":"@angular/router","name":"RouterModule","line":8,"character":25}],"declarations":[{"__symbolic":"reference","name":"ɵa"}],"exports":[{"__symbolic":"reference","name":"ɵa"}],"providers":[{"__symbolic":"reference","name":"CplxAlertService"}]}]}],"members":{},"statics":{"forRoot":{"__symbolic":"function","parameters":[],"value":{"ngModule":{"__symbolic":"reference","name":"CplxAlertModule"},"providers":[{"__symbolic":"reference","name":"CplxAlertService"},{"__symbolic":"reference","module":"@angular/router","name":"RouterModule","line":18,"character":33}]}}}},"ɵa":{"__symbolic":"class","decorators":[{"__symbolic":"call","expression":{"__symbolic":"reference","module":"@angular/core","name":"Component","line":5,"character":1},"arguments":[{"selector":"cplx-alert","template":"<div class=\"alerta-mensaje\">\r\n\t<div *ngFor=\"let m of alertas; let i = index\"\r\n\t\tclass=\"{{cssClass(m)}} ns-growl ns-box ns-effect-scale {{m.class}} px-2\">\r\n\t\t<div class=\"sms-box-inner\">\r\n\t\t\t<div class=\"d-flex\">\r\n\t\t\t\t<div class=\"pr-2 center-center\">\r\n\t\t\t\t\t<i class=\"fa fa-2x\" [ngClass]=\"{'fa-thumbs-o-up': m.tipo == 1 ,'fa-thumbs-o-down':m.tipo == 2 ,\r\n\t\t\t\t\t\t'fa-exclamation-circle':m.tipo == 3 ,'fa-bullseye':m.tipo == 4}\"></i>\r\n\t\t\t\t</div>\r\n\t\t\t\t<div>\r\n\t\t\t\t\t<label>{{m.mensaje}}.</label>\r\n\t\t\t\t</div>\r\n\t\t\t</div>\r\n\t\t</div>\r\n\t\t<i class=\"fa fa-times-circle fa-lg close\" aria-hidden=\"true\" style=\"cursor:pointer\"\r\n\t\t\t(click)=\"removerMensaje(m,i)\"></i>\r\n\t</div>\r\n</div>\r\n","styles":[".alerta-mensaje{position:fixed;top:40px;right:10px;z-index:1050;overflow:hidden;outline:0}.ns-effect-scale.ns-show{-webkit-animation-name:animateIn;animation-name:animateIn;-webkit-animation-duration:.25s;animation-duration:.25s}.ns-effect-scale.ns-hide{-webkit-animation-name:animateOut;animation-name:animateOut;-webkit-animation-duration:.25s;animation-duration:.25s;-webkit-animation-direction:reverse;animation-direction:reverse}.ns-effect-scale{box-shadow:0 25px 10px -15px rgba(0,0,0,.05)}.ns-growl{max-width:300px;min-width:300px;border-radius:5px}.ns-box{line-height:1.4;z-index:1000;font-size:90%;font-family:'Helvetica Neue','Segoe UI',Helvetica,Arial,sans-serif}.center-center{display:flex;flex-direction:column;justify-content:center;align-items:center}.close{width:20px!important;height:20px!important;position:absolute!important;right:4px!important;top:4px!important;cursor:pointer!important;-webkit-backface-visibility:hidden!important;backface-visibility:hidden!important}@-webkit-keyframes animateIn{0%{opacity:0;-webkit-transform:translate3d(0,40px,0) scale3d(.1,.6,1)}100%{opacity:1;-webkit-transform:translate3d(0,0,0) scale3d(1,1,1)}}@keyframes animateIn{0%{opacity:0;-webkit-transform:translate3d(0,40px,0) scale3d(.1,.6,1);transform:translate3d(0,40px,0) scale3d(.1,.6,1)}100%{opacity:1;-webkit-transform:translate3d(0,0,0) scale3d(1,1,1);transform:translate3d(0,0,0) scale3d(1,1,1)}}@-webkit-keyframes animateOut{0%{opacity:0;-webkit-transform:translate3d(0,40px,0) scale3d(.1,.6,1)}100%{opacity:1;-webkit-transform:translate3d(0,0,0) scale3d(1,1,1)}}@keyframes animateOut{0%{opacity:0;-webkit-transform:translate3d(0,40px,0) scale3d(.1,.6,1);transform:translate3d(0,40px,0) scale3d(.1,.6,1)}100%{opacity:1;-webkit-transform:translate3d(0,0,0) scale3d(1,1,1);transform:translate3d(0,0,0) scale3d(1,1,1)}}"]}]}],"members":{"timeout":[{"__symbolic":"property","decorators":[{"__symbolic":"call","expression":{"__symbolic":"reference","module":"@angular/core","name":"Input","line":15,"character":2}}]}],"__ctor__":[{"__symbolic":"constructor","parameters":[{"__symbolic":"reference","name":"CplxAlertService"}]}],"ngOnDestroy":[{"__symbolic":"method"}],"validate_mensaje":[{"__symbolic":"method"}],"removerMensaje":[{"__symbolic":"method"}],"cssClass":[{"__symbolic":"method"}],"cssClassIcon":[{"__symbolic":"method"}]}}},"origins":{"Alert":"./lib/cplx-alert.service","AlertType":"./lib/cplx-alert.service","CplxAlertService":"./lib/cplx-alert.service","CplxAlertModule":"./lib/cplx-alert.module","ɵa":"./lib/cplx-alert.component"},"importAs":"cplx-alert"}